asynctools/__init__.py
asynctools/daemon.py
asynctools/file.py
asynctools/libs.py
asynctools/res.py
asynctools/servers.py
asynctools/udp.py
x_mroy_1045-0.3.3.dist-info/METADATA
x_mroy_1045-0.3.3.dist-info/RECORD
x_mroy_1045-0.3.3.dist-info/WHEEL
x_mroy_1045-0.3.3.dist-info/entry_points.txt
x_mroy_1045-0.3.3.dist-info/top_level.txt
