Metadata-Version: 2.1
Name: x-mroy-1045
Version: 0.3.3
Summary: a anayzer package
Home-page: https://github.com/Qingluan/.git
Author: Qing luan
Author-email: darkhackdevil@gmail.com
License: MIT
Platform: UNKNOWN
Requires-Dist: async-timeout
Requires-Dist: bs4
Requires-Dist: lxml
Requires-Dist: termcolor
Requires-Dist: redis
Requires-Dist: aiofiles
Requires-Dist: aioredis
Requires-Dist: aiosocks (==0.2.6)
Requires-Dist: aiohttp (==2.3.10)
